pytorch_ssd/__init__.py
pytorch_ssd/args.py
pytorch_ssd/data/__init__.py
pytorch_ssd/data/bboxes.py
pytorch_ssd/data/datasets/__init__.py
pytorch_ssd/data/datasets/base.py
pytorch_ssd/data/datasets/clevr.py
pytorch_ssd/data/datasets/coco.py
pytorch_ssd/data/datasets/mnist.py
pytorch_ssd/data/datasets/mot15.py
pytorch_ssd/data/datasets/wider.py
pytorch_ssd/data/priors.py
pytorch_ssd/data/transforms.py
pytorch_ssd/main.py
pytorch_ssd/modeling/__init__.py
pytorch_ssd/modeling/backbones/__init__.py
pytorch_ssd/modeling/backbones/base.py
pytorch_ssd/modeling/backbones/mobilenetv2.py
pytorch_ssd/modeling/backbones/resnext.py
pytorch_ssd/modeling/backbones/vgg.py
pytorch_ssd/modeling/box_predictors/__init__.py
pytorch_ssd/modeling/box_predictors/ssd.py
pytorch_ssd/modeling/loss.py
pytorch_ssd/modeling/metrics.py
pytorch_ssd/modeling/model.py
pytorch_ssd/modeling/visualize.py
pytorch_ssd-1.8.0.dist-info/entry_points.txt
pytorch_ssd-1.8.0.dist-info/WHEEL
pytorch_ssd-1.8.0.dist-info/METADATA
pytorch_ssd-1.8.0.dist-info/RECORD
