Metadata-Version: 2.1
Name: pytorch-ssd
Version: 1.8.0
Summary: Single Shot Multi-Box Detector implementation in PyTorch
Author: PiotrJZielinski
Author-email: piotrekzie100@gmail.com
Requires-Python: >=3.8,<4.0
Classifier: Programming Language :: Python :: 3
Classifier: Programming Language :: Python :: 3.8
Classifier: Programming Language :: Python :: 3.9
Requires-Dist: albumentations (>=0.5.2,<0.6.0)
Requires-Dist: h5py (>=3.2.1,<4.0.0)
Requires-Dist: numpy (>=1.19.3,<2.0.0)
Requires-Dist: pillow (>=8.0.1,<9.0.0)
Requires-Dist: pycocotools (>=2.0.2,<3.0.0)
Requires-Dist: pytorch-lightning (>=1.1.2,<2.0.0)
Requires-Dist: torch (>=1.7.1,<2.0.0)
Requires-Dist: torchvision (>=0.8.2,<0.9.0)
Requires-Dist: wandb (>=0.10.12,<0.11.0)
